cats_refine/__init__.py
cats_refine/cats.py
cats_refine/utils.py
cats_refine-1.0.0.dist-info/licenses/LICENSE
cats_refine-1.0.0.dist-info/METADATA
cats_refine-1.0.0.dist-info/WHEEL
cats_refine-1.0.0.dist-info/top_level.txt
cats_refine-1.0.0.dist-info/RECORD
